djangocontact/__init__.py
djangocontact/admin.py
djangocontact/apps.py
djangocontact/urls.py
djangocontact/migrations/0001_initial.py
djangocontact/migrations/0002_auto_20200721_2308.py
djangocontact/migrations/__init__.py
djangocontact/migrations/__pycache__/0001_initial.cpython-38.pyc
djangocontact/migrations/__pycache__/0002_auto_20200721_2308.cpython-38.pyc
djangocontact/migrations/__pycache__/__init__.cpython-38.pyc
djangocontact/modeladmins/EmailModelAdmin.py
djangocontact/modeladmins/__init__.py
djangocontact/modeladmins/__pycache__/EmailModelAdmin.cpython-38.pyc
djangocontact/modeladmins/__pycache__/__init__.cpython-38.pyc
djangocontact/modelforms/EmailModelForm.py
djangocontact/modelforms/__init__.py
djangocontact/modelforms/__pycache__/EmailModelForm.cpython-38.pyc
djangocontact/modelforms/__pycache__/__init__.cpython-38.pyc
djangocontact/models/EmailModel.py
djangocontact/models/__init__.py
djangocontact/models/__pycache__/EmailModel.cpython-38.pyc
djangocontact/models/__pycache__/__init__.cpython-38.pyc
djangocontact/templates/djangoadmin/djangocontact/email_contact_view.html
djangocontact/templates/djangoadmin/djangocontact/simple_email_template.html
djangocontact/views/EmailContactView.py
djangocontact/views/__init__.py
djangocontact/views/__pycache__/EmailContactView.cpython-38.pyc
djangocontact/views/__pycache__/__init__.cpython-38.pyc
djangocontact-2.2.3.dist-info/License
djangocontact-2.2.3.dist-info/METADATA
djangocontact-2.2.3.dist-info/WHEEL
djangocontact-2.2.3.dist-info/top_level.txt
djangocontact-2.2.3.dist-info/RECORD
